LICENSE
README.md
setup.py
luogulib/__init__.py
luogulib/paintboard.py
luogulib.egg-info/PKG-INFO
luogulib.egg-info/SOURCES.txt
luogulib.egg-info/dependency_links.txt
luogulib.egg-info/requires.txt
luogulib.egg-info/top_level.txt